scidx_tools/__init__.py
scidx_tools/client/__init__.py
scidx_tools/client/consume_kafka.py
scidx_tools/client/init_client.py
scidx_tools/client/random_name.py
scidx_tools/client/send_random_messages.py
tests/__init__.py
tests/test_full_api_flow.py
tests/test_full_kafka_flow.py
scidx_tools-0.1.0.dist-info/AUTHORS
scidx_tools-0.1.0.dist-info/LICENSE
scidx_tools-0.1.0.dist-info/METADATA
scidx_tools-0.1.0.dist-info/WHEEL
scidx_tools-0.1.0.dist-info/top_level.txt
scidx_tools-0.1.0.dist-info/RECORD
