Metadata-Version: 2.1
Name: scidx-tools
Version: 0.1.0
Summary: Python client library for complementing the sciDX library
Home-page: https://github.com/sci-ndp/scidx-tools
Author: Andreu Fornos, Saleem Alharir, Raul Bardaji, Philip Davis, Ivan Rodero, Manish Parashar
Author-email: andreu.fornos@utah.edu, saleem.alharir@utah.edu, rbardaji@gmail.com, philip.e.davis@utah.edu, ivan.rodero@utah.edu, manish.parashar@utah.edu
License: UNKNOWN
Platform: UNKNOWN
Classifier: Programming Language :: Python :: 3
Classifier: License :: OSI Approved :: MIT License
Classifier: Operating System :: OS Independent
Requires-Python: >=3.6
License-File: LICENSE
License-File: AUTHORS
Requires-Dist: aiokafka
Requires-Dist: nest-asyncio
Requires-Dist: pandas
Requires-Dist: pytest
Requires-Dist: pytest-asyncio
Requires-Dist: pytest-order
Requires-Dist: requests
